mm_sol/__init__.py
mm_sol/account.py
mm_sol/constants.py
mm_sol/converters.py
mm_sol/py.typed
mm_sol/retry.py
mm_sol/rpc.py
mm_sol/rpc_sync.py
mm_sol/spl_token.py
mm_sol/transfer.py
mm_sol/utils.py
mm_sol/cli/__init__.py
mm_sol/cli/calcs.py
mm_sol/cli/cli.py
mm_sol/cli/cli_utils.py
mm_sol/cli/validators.py
mm_sol/cli/cmd/__init__.py
mm_sol/cli/cmd/balance_cmd.py
mm_sol/cli/cmd/balances_cmd.py
mm_sol/cli/cmd/example_cmd.py
mm_sol/cli/cmd/node_cmd.py
mm_sol/cli/cmd/transfer_cmd.py
mm_sol/cli/cmd/wallet/__init__.py
mm_sol/cli/cmd/wallet/keypair_cmd.py
mm_sol/cli/cmd/wallet/mnemonic_cmd.py
mm_sol/cli/examples/balances.toml
mm_sol/cli/examples/transfer.toml
mm_sol-0.7.4.dist-info/METADATA
mm_sol-0.7.4.dist-info/WHEEL
mm_sol-0.7.4.dist-info/entry_points.txt
mm_sol-0.7.4.dist-info/RECORD
