Metadata-Version: 2.4
Name: mm-sol
Version: 0.7.4
Requires-Python: >=3.13
Requires-Dist: base58~=2.1.1
Requires-Dist: jinja2~=3.1.6
Requires-Dist: mm-web3~=0.5.6
Requires-Dist: mnemonic==0.21
Requires-Dist: solana~=0.36.11
Requires-Dist: typer~=0.21.1
